easy_pdf/__init__.py
easy_pdf/apps.py
easy_pdf/exceptions.py
easy_pdf/models.py
easy_pdf/rendering.py
easy_pdf/tests.py
easy_pdf/views.py
easy_pdf/templates/easy_pdf/base.html
django_easy_pdf3-0.1.4.dist-info/LICENSE
django_easy_pdf3-0.1.4.dist-info/METADATA
django_easy_pdf3-0.1.4.dist-info/WHEEL
django_easy_pdf3-0.1.4.dist-info/top_level.txt
django_easy_pdf3-0.1.4.dist-info/RECORD
