Metadata-Version: 2.1
Name: django-easy-pdf3
Version: 0.1.4
Summary: Django PDF views, the easy way
Home-page: https://github.com/olksndrdevhub/django-easy-pdf3
Author: Filip Wasilewski
Author-email: en@ig.ma
Maintainer: Romaniuk Oleksandr
Maintainer-email: oleksandr.romaniuk@protonmail.com
License: MIT
Project-URL: Bug Tracker, https://github.com/olksndrdevhub/django-easy-pdf3/issues
Keywords: django-easy-pdf3
Platform: UNKNOWN
Classifier: Development Status :: 5 - Production/Stable
Classifier: Environment :: Web Environment
Classifier: Framework :: Django
Classifier: Intended Audience :: Developers
Classifier: License :: OSI Approved :: MIT License
Classifier: Operating System :: OS Independent
Classifier: Natural Language :: English
Classifier: Programming Language :: Python :: 2
Classifier: Programming Language :: Python :: 2.7
Classifier: Programming Language :: Python :: 3
Classifier: Programming Language :: Python :: 3.4
Classifier: Programming Language :: Python :: 3.5
Classifier: Programming Language :: Python :: 3.6
Classifier: Programming Language :: Python :: 3.8
Classifier: Programming Language :: Python :: 3.9
Classifier: Topic :: Software Development :: Libraries :: Python Modules
License-File: LICENSE
Requires-Dist: django (>=2.0)
Requires-Dist: xhtml2pdf (>=0.2b1)
Requires-Dist: reportlab (>=3)
